{
  "stories": [
    {
      "id": 2,
      "title": "naruto",
      "content": "những câu chuyện về chú mèo máy naruto",
      "view": 3000,
      "phatHanh": "1999",
      "theLoai": "hoạt hình"
    },
    {
      "id": 3,
      "title": "goku",
      "content": "những câu chuyện về chú mèo máy goku",
      "view": 5000,
      "phatHanh": "2000",
      "theLoai": "hoạt hình"
    },
    {
      "id": 4,
      "title": "Attack On Titan",
      "content": "những câu chuyện về chú mèo máy Attack On Titan",
      "view": 7000,
      "phatHanh": "2009",
      "theLoai": "hoạt hình"
    },
    {
      "id": 5,
      "title": "Bleach",
      "content": "những câu chuyện về chú mèo máy Bleach",
      "view": 6000,
      "phatHanh": "2004",
      "theLoai": "hoạt hình"
    },
    {
      "id": 7,
      "title": "cc",
      "content": "cc",
      "view": 123,
      "PhatHanh": "",
      "theLoai": "cc"
    },
    {
      "id": 8,
      "title": "bb",
      "content": "bb",
      "view": 222,
      "PhatHanh": "",
      "theLoai": "bb"
    },
    {
      "id": 9,
      "title": "vv",
      "content": "vv",
      "view": 123,
      "PhatHanh": "",
      "theLoai": "vv"
    },
    {
      "title": "ss",
      "content": "ss",
      "view": 112,
      "phatHanh": "2026-07-18",
      "theLoai": "ss",
      "id": 10
    }
  ]
}